onir/__init__.py
onir/config.py
onir/log.py
onir/random.py
onir/spec.py
onir/datasets/__init__.py
onir/datasets/antique.py
onir/datasets/base.py
onir/datasets/car.py
onir/datasets/covid.py
onir/datasets/doc_iter.py
onir/datasets/flex.py
onir/datasets/index_backed.py
onir/datasets/msmarco.py
onir/datasets/multilingual_dataset.py
onir/datasets/nyt.py
onir/datasets/pair_iter.py
onir/datasets/query_iter.py
onir/datasets/random.py
onir/datasets/record_iter.py
onir/datasets/robust.py
onir/datasets/trec_arabic.py
onir/datasets/trec_mandarin.py
onir/datasets/trec_spanish.py
onir/datasets/utils.py
onir/datasets/wikir.py
onir/indices/__init__.py
onir/indices/anserini.py
onir/indices/base.py
onir/indices/misc.py
onir/indices/multifield_anserini.py
onir/indices/multifield_sqlite.py
onir/indices/sqlite.py
onir/interfaces/__init__.py
onir/interfaces/apex.py
onir/interfaces/bert_models.py
onir/interfaces/car.py
onir/interfaces/java.py
onir/interfaces/matchzoo.py
onir/interfaces/msmarco_eval.py
onir/interfaces/plaintext.py
onir/interfaces/sqlite.py
onir/interfaces/trec.py
onir/interfaces/wordvec.py
onir/modules/__init__.py
onir/modules/bert.py
onir/modules/interaction_matrix.py
onir/modules/rbf_kernels.py
onir/predictors/__init__.py
onir/predictors/base.py
onir/predictors/reranker.py
onir/rankers/__init__.py
onir/rankers/base.py
onir/rankers/cedr_drmm.py
onir/rankers/cedr_knrm.py
onir/rankers/cedr_pacrr.py
onir/rankers/conv_knrm.py
onir/rankers/drmm.py
onir/rankers/duetl.py
onir/rankers/epic.py
onir/rankers/knrm.py
onir/rankers/matchpyramid.py
onir/rankers/matchzoo.py
onir/rankers/pacrr.py
onir/rankers/trivial.py
onir/rankers/vanilla_transformer.py
onir/tasks/__init__.py
onir/tasks/evaluate.py
onir/tasks/learner.py
onir/trainers/__init__.py
onir/trainers/base.py
onir/trainers/misc.py
onir/trainers/pairwise.py
onir/trainers/pointwise.py
onir/trainers/trivial.py
onir/util/__init__.py
onir/util/concurrency.py
onir/util/download.py
onir/util/matheval.py
onir/vocab/__init__.py
OpenNIR_XPM-0.1.4.dist-info/LICENSE.txt
OpenNIR_XPM-0.1.4.dist-info/METADATA
OpenNIR_XPM-0.1.4.dist-info/WHEEL
OpenNIR_XPM-0.1.4.dist-info/top_level.txt
OpenNIR_XPM-0.1.4.dist-info/RECORD
