Metadata-Version: 2.1
Name: OpenNIR-XPM
Version: 0.1.4
Summary: OpenNIR: A Complete Neural Ad-Hoc Ranking Pipeline (Experimaestro version)
Home-page: https://github.com/bpiwowar/OpenNIR-xpm
Author: Sean MacAvaney (adapted by Benjamin Piwowarski for experimaestro)
Author-email: b@piwowarski.fr
License: UNKNOWN
Project-URL: Documentation, https://github.com/bpiwowar/OpenNIR-xpm
Project-URL: Source, https://github.com/bpiwowar/OpenNIR-xpm
Platform: UNKNOWN
Requires-Python: >=3.7
Requires-Dist: torch
Requires-Dist: pytorch-pretrained-bert
Requires-Dist: pytorch-transformers
Requires-Dist: tokenizers
Requires-Dist: tqdm
Requires-Dist: colorlog
Requires-Dist: terminaltables
Requires-Dist: matplotlib
Requires-Dist: seaborn
Requires-Dist: python-ternary
Requires-Dist: beautifulsoup4
Requires-Dist: Unidecode
Requires-Dist: nltk
Requires-Dist: sqlitedict
Requires-Dist: pytrec-eval (>=0.5)
Requires-Dist: gensim
Requires-Dist: Cython
Requires-Dist: pyjnius
Requires-Dist: pytools
Requires-Dist: cached-property
Requires-Dist: experimaestro-ir (>=0.1.1)
Requires-Dist: experimaestro (>=0.7.4)
